dumbledore/__init__.py
dumbledore/basics.py
dumbledore/transform.py
dumbledore-0.0.5.dist-info/LICENSE
dumbledore-0.0.5.dist-info/METADATA
dumbledore-0.0.5.dist-info/WHEEL
dumbledore-0.0.5.dist-info/top_level.txt
dumbledore-0.0.5.dist-info/RECORD
