Metadata-Version: 2.1
Name: dumbledore
Version: 0.0.5
Summary: a python package to visvalize features of data and observe relation without writing lots of codes
Home-page: https://github.com/imZain448/dumbledore
Author: imzain448
Author-email: ahmadzain.448@gmail.com
License: UNKNOWN
Platform: UNKNOWN
Classifier: Programming Language :: Python :: 3
Classifier: License :: OSI Approved :: GNU General Public License v3 (GPLv3)
Classifier: Operating System :: OS Independent
Requires-Python: >=3.6
Requires-Dist: matplotlib
Requires-Dist: seaborn
Requires-Dist: pandas
Requires-Dist: numpy
Requires-Dist: scipy
Requires-Dist: sklearn
